<?xml version="1.0" encoding="utf-8" ?>
<dwsync>
<file name=".editorconfig" server="sftp.itd.umich.edu//afs/umich.edu/group/m/michitdv/Public/html/" local="131515294220000000" remote="131515294220000000" Dst="1" />
<file name=".gitignore" server="sftp.itd.umich.edu//afs/umich.edu/group/m/michitdv/Public/html/" local="131515294220000000" remote="131515294220000000" Dst="1" />
<file name=".htaccess" server="sftp.itd.umich.edu//afs/umich.edu/group/m/michitdv/Public/html/" local="131564506920000000" remote="131564506920000000" Dst="1" />
<file name="authorize.php" server="sftp.itd.umich.edu//afs/umich.edu/group/m/michitdv/Public/html/" local="131515294230000000" remote="131515294230000000" Dst="1" />
<file name="CHANGELOG.txt" server="sftp.itd.umich.edu//afs/umich.edu/group/m/michitdv/Public/html/" local="131515294230000000" remote="131515294230000000" Dst="1" />
<file name="COPYRIGHT.txt" server="sftp.itd.umich.edu//afs/umich.edu/group/m/michitdv/Public/html/" local="131515294230000000" remote="131515294230000000" Dst="1" />
<file name="cron.php" server="sftp.itd.umich.edu//afs/umich.edu/group/m/michitdv/Public/html/" local="131515294230000000" remote="131515294230000000" Dst="1" />
<file name="index.php" server="sftp.itd.umich.edu//afs/umich.edu/group/m/michitdv/Public/html/" local="131515294230000000" remote="131515294230000000" Dst="1" />
<file name="INSTALL.mysql.txt" server="sftp.itd.umich.edu//afs/umich.edu/group/m/michitdv/Public/html/" local="131515294230000000" remote="131515294230000000" Dst="1" />
<file name="INSTALL.pgsql.txt" server="sftp.itd.umich.edu//afs/umich.edu/group/m/michitdv/Public/html/" local="131515294230000000" remote="131515294230000000" Dst="1" />
<file name="install.php" server="sftp.itd.umich.edu//afs/umich.edu/group/m/michitdv/Public/html/" local="131515294230000000" remote="131515294230000000" Dst="1" />
<file name="INSTALL.sqlite.txt" server="sftp.itd.umich.edu//afs/umich.edu/group/m/michitdv/Public/html/" local="131515294230000000" remote="131515294230000000" Dst="1" />
<file name="INSTALL.txt" server="sftp.itd.umich.edu//afs/umich.edu/group/m/michitdv/Public/html/" local="131515294240000000" remote="131515294240000000" Dst="1" />
<file name="LICENSE.txt" server="sftp.itd.umich.edu//afs/umich.edu/group/m/michitdv/Public/html/" local="131515294240000000" remote="131515294240000000" Dst="1" />
<file name="MAINTAINERS.txt" server="sftp.itd.umich.edu//afs/umich.edu/group/m/michitdv/Public/html/" local="131515294240000000" remote="131515294240000000" Dst="1" />
<file name="README.txt" server="sftp.itd.umich.edu//afs/umich.edu/group/m/michitdv/Public/html/" local="131515294240000000" remote="131515294240000000" Dst="1" />
<file name="robots.txt" server="sftp.itd.umich.edu//afs/umich.edu/group/m/michitdv/Public/html/" local="131515294240000000" remote="131515294240000000" Dst="1" />
<file name="update.php" server="sftp.itd.umich.edu//afs/umich.edu/group/m/michitdv/Public/html/" local="131515294240000000" remote="131515294240000000" Dst="1" />
<file name="UPGRADE.txt" server="sftp.itd.umich.edu//afs/umich.edu/group/m/michitdv/Public/html/" local="131515294240000000" remote="131515294240000000" Dst="1" />
<file name="web.config" server="sftp.itd.umich.edu//afs/umich.edu/group/m/michitdv/Public/html/" local="131515294240000000" remote="131515294240000000" Dst="1" />
<file name="xmlrpc.php" server="sftp.itd.umich.edu//afs/umich.edu/group/m/michitdv/Public/html/" local="131515294240000000" remote="131515294240000000" Dst="1" />
</dwsync>